{
  "_type": "lesson",
  "_id": "lesson-bab-5",
  "title": "Bab 5: どこへ行きますか (Pergerakan, Transportasi, & Tanggal)",
  "slug": {
    "_type": "slug",
    "current": "bab-5"
  },
  "order_number": 5,
  "category_id": "N5-Course",
  "summary": "Setelah menguasai rutinitas waktu di Bab 4, sekarang saatnya Anda \"bergerak\". Setelah menyelesaikan bab ini, Anda ditargetkan mampu:",
  "estimated_minutes": 15,
  "is_premium": false,
  "is_published": true,
  "vocab_list": [
    "行きます",
    "来ます",
    "帰ります",
    "電車",
    "地下鉄",
    "新幹線",
    "バス",
    "タクシー",
    "自転車",
    "飛行機",
    "船",
    "歩いて",
    "駅",
    "友達",
    "彼",
    "彼女",
    "恋人",
    "家族",
    "一人で",
    "会社",
    "コンビニ",
    "レストラン",
    "公園",
    "先週",
    "今週",
    "来週",
    "先月",
    "今月",
    "来月",
    "去年",
    "今年",
    "来年",
    "いつ",
    "誕生日",
    "月",
    "日",
    "次",
    "どうやって",
    "いいですね",
    "そうですね"
  ],
  "kanji_list": [
    "土",
    "行",
    "来",
    "車",
    "年"
  ],
  "grammar_list": [
    "[Tempat] へ 行きます/来ます/帰ります",
    "[Kendaraan] で 行きます",
    "[Orang] と 行きます",
    "いつ (Itsu)"
  ],
  "reading_list": [],
  "listening_list": [],
  "seo": {
    "title": "Belajar Bab 5 Bahasa Jepang N5 - どこへ行きますか (Pergerakan, Transportasi, & Tanggal) | NihongoRoute",
    "description": "Kuasai materi pelajaran Bahasa Jepang N5 Bab 5: どこへ行きますか (Pergerakan, Transportasi, & Tanggal). Kosakata, Kanji, Tata Bahasa, Percakapan, dan Kuis interaktif.",
    "keywords": "NihongoRoute, N5, Bab 5, どこへ行きますか (Pergerakan, Transportasi, & Tanggal), Bahasa Jepang"
  },
  "content_blocks": [
    {
      "_type": "block",
      "style": "h2",
      "children": [
        {
          "_type": "span",
          "text": "🎯 1. Tujuan Belajar (Can-Do Objectives)"
        }
      ]
    },
    {
      "_type": "block",
      "style": "normal",
      "children": [
        {
          "_type": "span",
          "text": "Setelah menguasai rutinitas waktu di Bab 4, sekarang saatnya Anda \"bergerak\". Setelah menyelesaikan bab ini, Anda ditargetkan mampu:"
        }
      ]
    },
    {
      "_type": "block",
      "style": "normal",
      "children": [
        {
          "_type": "span",
          "text": "• Menyatakan ke mana Anda akan pergi, datang, atau pulang.\n• Menjelaskan alat transportasi yang digunakan untuk menuju suatu tempat.\n• Menceritakan dengan siapa Anda bepergian.\n• Bertanya dan menjawab tentang keterangan waktu relatif (Kapan, Bulan depan, Tahun lalu)."
        }
      ]
    },
    {
      "_type": "block",
      "style": "h2",
      "children": [
        {
          "_type": "span",
          "text": "📖 2. Bedah Kosakata (40 Kata)"
        }
      ]
    },
    {
      "_type": "block",
      "style": "normal",
      "children": [
        {
          "_type": "span",
          "text": "Format: Kanji (Hiragana - Romaji) : Arti"
        }
      ]
    },
    {
      "_type": "vocabBlock",
      "title": "Daftar Kosakata"
    },
    {
      "_type": "block",
      "style": "h2",
      "children": [
        {
          "_type": "span",
          "text": "🛠️ 3. Tata Bahasa Ekstensif"
        }
      ]
    },
    {
      "_type": "grammarBlock",
      "title": "A. Partikel Arah/Tujuan: [Tempat] へ 行きます/来ます/帰ります",
      "content": "[Tempat] へ 行きます/来ます/帰ります",
      "furigana": "",
      "translation": "Partikel へ (ditulis dengan huruf *he*, tetapi dibaca **e**) menandakan arah atau tujuan pergerakan.",
      "examples": [
        {
          "jp": "* 京都へ行きます。",
          "romaji": "Kyouto e ikimasu.",
          "id": "Saya pergi ke Kyoto.",
          "furigana": ""
        }
      ]
    },
    {
      "_type": "grammarBlock",
      "title": "B. Partikel Kendaraan/Metode: [Kendaraan] で 行きます",
      "content": "[Kendaraan] で 行きます",
      "furigana": "",
      "translation": "Partikel で (de) digunakan untuk menyatakan alat atau sarana, dalam hal ini adalah alat transportasi yang digunakan (\"dengan/naik\").",
      "examples": [
        {
          "jp": "* バスで会社へ行きます。",
          "romaji": "Basu de kaisha e ikimasu.",
          "id": "Saya pergi ke kantor naik bus.",
          "furigana": ""
        }
      ]
    },
    {
      "_type": "grammarBlock",
      "title": "C. Partikel Teman Perjalanan: [Orang] と 行きます",
      "content": "[Orang] と 行きます",
      "furigana": "",
      "translation": "Partikel と (to) digunakan untuk menyatakan partner/teman yang menyertai aktivitas Anda (\"bersama\").",
      "examples": [
        {
          "jp": "* 家族と日本へ来ました。",
          "romaji": "Kazoku to Nihon e kimashita.",
          "id": "Saya datang ke Jepang bersama keluarga.",
          "furigana": ""
        }
      ]
    },
    {
      "_type": "grammarBlock",
      "title": "D. Menanyakan Waktu Tanpa Angka Pasti: いつ (Itsu)",
      "content": "いつ (Itsu)",
      "furigana": "",
      "translation": "Kata いつ (Kapan) digunakan untuk menanyakan waktu. Berbeda dengan *Nan-ji* (Jam berapa) atau *Nan-youbi* (Hari apa), kata *Itsu* **TIDAK BOLEH** diikuti oleh partikel に (ni).",
      "examples": [
        {
          "jp": "* いつインドネシアへ来ましたか。(Itsu Indoneshia e kimashita ka. - Kapan Anda datang ke Indonesia?) -> *Bukan \"Itsu ni...\"*",
          "romaji": "",
          "id": "",
          "furigana": ""
        }
      ]
    },
    {
      "_type": "block",
      "style": "h2",
      "children": [
        {
          "_type": "span",
          "text": "🖌️ 4. Daftar Kanji Dasar (Bab 5)"
        }
      ]
    },
    {
      "_type": "block",
      "style": "normal",
      "children": [
        {
          "_type": "span",
          "text": "Detail urutan coretan (stroke order) dan gabungan kata dapat dilihat di rute halaman eksplorasi Kanji."
        }
      ]
    },
    {
      "_type": "kanjiBlock",
      "title": "Daftar Kanji"
    },
    {
      "_type": "block",
      "style": "h2",
      "children": [
        {
          "_type": "span",
          "text": "⛩️ 5. Catatan Budaya (Etiket & Transportasi)"
        }
      ]
    },
    {
      "_type": "calloutBlock",
      "title": "Tata Krama Kereta (Densha no Maner)",
      "content": "Transportasi umum di Jepang sangat hening. Berbicara di telepon (menelepon) saat berada di dalam kereta atau bus dianggap sangat tidak sopan. Penumpang diwajibkan mengubah ponsel ke mode diam (*Manner mode*)."
    },
    {
      "_type": "calloutBlock",
      "title": "Konsep \"Kaerimasu\" (Pulang)",
      "content": "Kata kerja *Kaerimasu* tidak bisa digunakan untuk semua tempat. Kata ini hanya eksklusif digunakan untuk kembali ke \"tempat asal/naungan\" Anda, seperti *Uchi* (Rumah), *Kuni* (Negara asal), atau *Kaisha* (Perusahaan/Kantor sendiri tempat Anda bernaung)."
    },
    {
      "_type": "block",
      "style": "h2",
      "children": [
        {
          "_type": "span",
          "text": "💬 6. Praktik Membaca Nyata (Dialog)"
        }
      ]
    },
    {
      "_type": "dialogueBlock",
      "title": "Praktik Membaca Nyata (Dialog)",
      "content": "田中：ブディさん、いつ日本へ来ましたか。\nブディ：去年の９月に来ました。\n田中：そうですか。誰と来ましたか。\nブディ：一人で来ました。\n田中：いいですね。明日、どこへ行きますか。\nブディ：京都へ行きます。\n田中：どうやって行きますか。バスですか。\nブディ：いいえ、新幹線で行きます。彼女と行きます。",
      "translation": "Tanaka: san, itsu Nihon e kimashita ka. - Tuan Budi, kapan Anda datang ke Jepang?\nBudi: gatsu ni kimashita. - Saya datang pada bulan September tahun lalu.\nTanaka: Oh, begitu. Anda datang bersama siapa?\nBudi: Saya datang sendirian.\nTanaka: Bagus ya. Besok Anda akan pergi ke mana?\nBudi: Saya akan pergi ke Kyoto.\nTanaka: Bagaimana cara perginya? Apakah naik bus?\nBudi: Tidak, saya pergi naik Shinkansen (kereta peluru",
      "furigana": ""
    },
    {
      "_type": "block",
      "style": "h2",
      "children": [
        {
          "_type": "span",
          "text": "✏️ 7. Kuis Evaluasi Bab 5"
        }
      ]
    }
  ],
  "quizzes": [
    {
      "id": "n5-bab5-q1",
      "question": "Partikel yang digunakan untuk menandakan arah tujuan setelah kata tempat (dibaca 'e') ditulis dengan huruf Hiragana apa?",
      "options": [
        "え",
        "へ",
        "に"
      ],
      "correct_answer": "へ",
      "explanation": "Partikel arah dibaca \"e\", namun penulisannya selalu menggunakan huruf Hiragana \"he\" (へ).",
      "type": "multiple-choice"
    },
    {
      "id": "n5-bab5-q2",
      "question": "\"Saya pergi ke taman dengan berjalan kaki.\" Kalimat bahasa Jepang yang **Tepat** adalah...",
      "options": [
        "歩いてで公園へ行きます。(Aruite de kouen e ikimasu.)",
        "歩いてと公園へ行きます。(Aruite to kouen e ikimasu.)",
        "歩いて公園へ行きます。(Aruite kouen e ikimasu.)"
      ],
      "correct_answer": "歩いて公園へ行きます。(Aruite kouen e ikimasu.)",
      "explanation": "Kata \"Aruite\" (dengan berjalan kaki) adalah bentuk pengecualian. Anda dilarang keras menempelkan partikel \"de\" atau partikel sarana lainnya setelah kata ini.",
      "type": "multiple-choice"
    },
    {
      "id": "n5-bab5-q3",
      "question": "Anda pergi makan ke restoran sendirian. Bagaimana Anda mengucapkannya?",
      "options": [
        "友達とレストランへ行きます。(Tomodachi to resutoran e ikimasu.)",
        "家族とレストランへ行きます。(Kazoku to resutoran e ikimasu.)",
        "一人でレストランへ行きます。(Hitori de resutoran e ikimasu.)"
      ],
      "correct_answer": "一人でレストランへ行きます。(Hitori de resutoran e ikimasu.)",
      "explanation": "\"Hitori de\" artinya sendirian. Sama seperti Aruite, \"Hitori de\" juga tidak boleh ditempelkan partikel teman \"to\" meskipun konteks kalimatnya membicarakan partner perjalanan.",
      "type": "multiple-choice"
    },
    {
      "id": "n5-bab5-q4",
      "question": "Kalimat mana yang menggunakan kata tanya dan partikel dengan tata bahasa yang **BENAR**?",
      "options": [
        "いつにうちへ帰りますか。(Itsu ni uchi e kaerimasu ka.)",
        "いつうちへ帰りますか。(Itsu uchi e kaerimasu ka.)",
        "何時うちへ帰りますか。(Nanji uchi e kaerimasu ka.)"
      ],
      "correct_answer": "いつうちへ帰りますか。(Itsu uchi e kaerimasu ka.)",
      "explanation": "Kata tanya \"Itsu\" (Kapan) bersifat relatif dan mandiri, sehingga tidak boleh diikuti oleh partikel \"ni\". Pilihan C salah karena \"Nanji\" wajib menggunakan partikel \"ni\" (Nanji ni).",
      "type": "multiple-choice"
    },
    {
      "id": "n5-bab5-q5",
      "question": "*Lengkapi percakapan berikut:*\nA: 日曜日はどこ（ ____ ）行きましたか。(Nichiyoubi wa doko ____ ikimashita ka.)\nB: どこ（ ____ ）行きませんでした。(Doko ____ ikimasen deshita.)",
      "options": [
        "へ / も (e / mo)",
        "に / も (ni / mo)",
        "へ / へ (e / e)"
      ],
      "correct_answer": "へ / も (e / mo)",
      "explanation": "\"Doko e\" artinya \"ke mana\". Untuk menyatakan penyangkalan total (\"tidak ke mana-mana\"), gunakan pola *Kata Tanya + partikel 'mo' + kata kerja negatif* (Doko e mo ikimasen deshita).",
      "type": "multiple-choice"
    },
    {
      "id": "n5-bab5-q6",
      "question": "Kanji \"車\" (Kuruma/Sha) melambangkan benda apa?",
      "options": [
        "Kereta bawah tanah",
        "Sepeda",
        "Mobil / Kendaraan beroda"
      ],
      "correct_answer": "Mobil / Kendaraan beroda",
      "explanation": "Kanji 車 (Kuruma) secara visual berbentuk seperti gerobak atau as roda dilihat dari atas, dan merepresentasikan mobil atau kendaraan bermotor/beroda secara umum.",
      "type": "multiple-choice"
    },
    {
      "id": "n5-bab5-q7",
      "question": "Terjemahan yang tepat untuk kata \"Kyonen\" (去年) dan \"Raishuu\" (来週) secara berurutan adalah...",
      "options": [
        "Tahun lalu dan Minggu depan",
        "Tahun ini dan Bulan depan",
        "Bulan lalu dan Minggu ini"
      ],
      "correct_answer": "Tahun lalu dan Minggu depan",
      "explanation": "去年 (Kyo-nen) berarti Tahun lalu. 来週 (Rai-shuu) berarti Minggu depan.",
      "type": "multiple-choice"
    },
    {
      "id": "n5-bab5-q8",
      "question": "Hal apa yang dianggap tabu (tidak sopan) dilakukan saat berada di dalam kereta api di Jepang?",
      "options": [
        "Membaca buku (Hon o yomimasu)",
        "Tidur (Nemasu)",
        "Berbicara di telepon (Menelepon)"
      ],
      "correct_answer": "Berbicara di telepon (Menelepon)",
      "explanation": "Mengobrol menggunakan telepon genggam di dalam angkutan umum sangat dilarang karena mengganggu ketenangan publik.",
      "type": "multiple-choice"
    },
    {
      "id": "n5-bab5-q9",
      "question": "\"Datang ke sekolah naik sepeda bersama teman\". Susunan partikel yang tepat adalah...",
      "options": [
        "友達（で）自転車（と）学校（へ）来ました。(Tomodachi de jitensha to gakkou e kimashita.)",
        "友達（と）自転車（で）学校（へ）来ました。(Tomodachi to jitensha de gakkou e kimashita.)",
        "友達（へ）自転車（で）学校（と）来ました。(Tomodachi e jitensha de gakkou to kimashita.)"
      ],
      "correct_answer": "友達（と）自転車（で）学校（へ）来ました。(Tomodachi to jitensha de gakkou e kimashita.)",
      "explanation": "*Teman* adalah orang, jadi menggunakan partikel と (to). *Sepeda* adalah alat transportasi, jadi menggunakan partikel で (de). *Sekolah* adalah tempat tujuan, menggunakan partikel へ (e).",
      "type": "multiple-choice"
    },
    {
      "id": "n5-bab5-q10",
      "question": "Berdasarkan teks dialog, dengan kendaraan apa Budi akan pergi ke Kyoto besok?",
      "options": [
        "バス (Bus)",
        "飛行機 (Pesawat)",
        "新幹線 (Kereta peluru / Shinkansen)"
      ],
      "correct_answer": "新幹線 (Kereta peluru / Shinkansen)",
      "explanation": "Dalam dialog, Tanaka bertanya \"Bus desu ka?\", dan Budi membantah dengan \"Iie, shinkansen de ikimasu\" (Bukan, saya pergi dengan Shinkansen).",
      "type": "multiple-choice"
    }
  ]
}